MANIFEST.in
README.rst
requirements-dev.txt
setup.cfg
setup.py
downburst/__init__.py
downburst/cli.py
downburst/create.py
downburst/dehumanize.py
downburst/destroy.py
downburst/discover.py
downburst/exc.py
downburst/gen_ssh_key.py
downburst/image.py
downburst/iso.py
downburst/meta.py
downburst/template.py
downburst/wait.py
downburst.egg-info/PKG-INFO
downburst.egg-info/SOURCES.txt
downburst.egg-info/dependency_links.txt
downburst.egg-info/entry_points.txt
downburst.egg-info/requires.txt
downburst.egg-info/top_level.txt
downburst/test/__init__.py
downburst/test/test_dehumanize.py
downburst/test/test_discover.py
downburst/test/test_template.py