Metadata-Version: 1.1
Name: downburst
Version: 0.0.1
Summary: Run Cloud images on libvirt virtual machines
Home-page: https://github.com/ceph/downburst
Author: Inktank Storage, Inc.
Author-email: ceph-qa@ceph.com
License: MIT
Keywords: libvirt virtualization
Platform: UNKNOWN
Classifier: Intended Audience :: Developers
Classifier: Intended Audience :: Information Technology
Classifier: License :: OSI Approved :: MIT License
Classifier: Natural Language :: English
Classifier: Operating System :: POSIX :: Linux
Classifier: Programming Language :: Python :: 2.7
